Metadata-Version: 1.1
Name: unauthorized-page
Version: 0.0.2
Summary: A simple decorator to handle views for authorized sessions
Home-page: UNKNOWN
Author: Ankit Kumar
Author-email: ankitkumar0411@gmail.com
License: MIT
Keywords: decorator
Platform: UNKNOWN
Classifier: Development Status :: 5 - Production/Stable
Classifier: Intended Audience :: Developers
Classifier: Operating System :: Microsoft :: Windows :: Windows 10
Classifier: License :: OSI Approved :: MIT License
Classifier: Programming Language :: Python :: 3
